Metadata-Version: 2.1
Name: torch-transformer
Version: 0.18.1
Summary: Transformer implemented in PyTorch
Home-page: https://github.com/CyberZHG/torch-transformer
Author: CyberZHG
Author-email: CyberZHG@gmail.com
License: MIT
Platform: UNKNOWN
Classifier: Programming Language :: Python :: 2.7
Classifier: Programming Language :: Python :: 3.6
Classifier: License :: OSI Approved :: MIT License
Classifier: Operating System :: OS Independent
